MANIFEST.in
README.rst
setup.py
src/pysistor/__init__.py
src/pysistor/backends.py
src/pysistor/tests.py
src/pysistor.egg-info/PKG-INFO
src/pysistor.egg-info/SOURCES.txt
src/pysistor.egg-info/dependency_links.txt
src/pysistor.egg-info/top_level.txt