Metadata-Version: 1.0
Name: pysistor
Version: 0.1.1
Summary: A Python framework for CAPTCHA tests
Home-page: UNKNOWN
Author: Isaac Cook
Author-email: isaac@simpload.com
License: MIT
Platform: UNKNOWN
